odoo/addons/website_sale_product_attachment/README.rst
odoo/addons/website_sale_product_attachment/__init__.py
odoo/addons/website_sale_product_attachment/__manifest__.py
odoo/addons/website_sale_product_attachment/controllers/__init__.py
odoo/addons/website_sale_product_attachment/controllers/main.py
odoo/addons/website_sale_product_attachment/i18n/es.po
odoo/addons/website_sale_product_attachment/i18n/website_sale_product_attachment.pot
odoo/addons/website_sale_product_attachment/models/__init__.py
odoo/addons/website_sale_product_attachment/models/ir_attachment.py
odoo/addons/website_sale_product_attachment/models/product_template.py
odoo/addons/website_sale_product_attachment/readme/CONFIGURE.rst
odoo/addons/website_sale_product_attachment/readme/CONTRIBUTORS.rst
odoo/addons/website_sale_product_attachment/readme/DESCRIPTION.rst
odoo/addons/website_sale_product_attachment/readme/ROADMAP.rst
odoo/addons/website_sale_product_attachment/readme/USAGE.rst
odoo/addons/website_sale_product_attachment/static/description/backend-attachment.png
odoo/addons/website_sale_product_attachment/static/description/backend-product.png
odoo/addons/website_sale_product_attachment/static/description/frontend-download.gif
odoo/addons/website_sale_product_attachment/static/description/frontend-icons.png
odoo/addons/website_sale_product_attachment/static/description/icon.png
odoo/addons/website_sale_product_attachment/static/description/index.html
odoo/addons/website_sale_product_attachment/templates/product_template.xml
odoo/addons/website_sale_product_attachment/views/ir_attachment.xml
odoo/addons/website_sale_product_attachment/views/product_template.xml
odoo12_addon_website_sale_product_attachment-12.0.1.1.1.dist-info/METADATA
odoo12_addon_website_sale_product_attachment-12.0.1.1.1.dist-info/WHEEL
odoo12_addon_website_sale_product_attachment-12.0.1.1.1.dist-info/top_level.txt
odoo12_addon_website_sale_product_attachment-12.0.1.1.1.dist-info/RECORD
